{"count": 81, "totalAds": 81, "isResultsLimitReached": false, "results": [{"realEstate": {"advertiser": {"agency": {"id": 41729, "type": "agency", "label": "agenzia", "displayName": "Milano Marghera Real Estate", "imageUrls": {"small": "https://pic.im-cdn.it/imagenoresize/460000939.jpg", "large": "https://pic.im-cdn.it/imagenoresize/460000943.jpg"}, "agencyUrl": "https://www.immobiliare.it/agenzie-immobiliari/41729/milano-marghera/", "phones": [{"type": "tel1", "value": "02 3656 0866"}, {"type": "cell", "value": "393 937 2223"}], "isPaid": true, "customType": null, "externalLinks": null, "text": null, "track": null, "guaranteed": null}, "supervisor": null, "hasCallNumbers": true}, "contract": "sale", "id": 84693776, "isNew": false, "luxury": true, "price": {"minValue": null, "maxValue": null, "value": 970000, "formattedValue": "\u20ac 970.000", "formattedValueTop": "\u20ac 970.000", "visible": true, "loweredPrice": null}, "properties": [{"auction": null, "bathrooms": "1", "caption": null, "category": {"id": 1, "name": "Residenziale"}, "description": "PIAZZA DE ANGELI: In ottimo stabile vecchia Milano con ascensore, splendido appartamento su due livelli con splendida vista panoramica su piazza De Angeli e Via Marghera, composto da ingresso sul salone con cucina a vista e ampia camera o sala da pranzo a seconda delle necessit\u00e0 con possibilit\u00e0 di creare il bagno. Al quinto ed ultimo piano, tramite una comoda scala troviamo un secondo ingresso, un soggiorno/studio, due camere ed un ampio bagno. Classe Energetica: G EPI: 175,00 kwh/m2 anno", "floor": {"abbreviation": "4", "value": "4\u00b0, con ascensore"}, "multimedia": {"photos": [{"id": 998928928, "caption": "Salone", "urls": {"small": "https://pwm.im-cdn.it/image/998928928/xxs-c.jpg"}}, {"id": 998928932, "caption": "Salone", "urls": {"small": "https://pwm.im-cdn.it/image/998928932/xxs-c.jpg"}}, {"id": 998928934, "caption": "Salone", "urls": {"small": "https://pwm.im-cdn.it/image/998928934/xxs-c.jpg"}}, {"id": 998928936, "caption": "Salone", "urls": {"small": "https://pwm.im-cdn.it/image/998928936/xxs-c.jpg"}}, {"id": 998928942, "caption": "camera/studio", "urls": {"small": "https://pwm.im-cdn.it/image/998928942/xxs-c.jpg"}}, {"id": 998928950, "caption": "camera/studio", "urls": {"small": "https://pwm.im-cdn.it/image/998928950/xxs-c.jpg"}}, {"id": 998928958, "caption": "Camera", "urls": {"small": "https://pwm.im-cdn.it/image/998928958/xxs-c.jpg"}}, {"id": 998928970, "caption": "Bagno", "urls": {"small": "https://pwm.im-cdn.it/image/998928970/xxs-c.jpg"}}, {"id": 998928974, "caption": "Contesto", "urls": {"small": "https://pwm.im-cdn.it/image/998928974/xxs-c.jpg"}}, {"id": 998928980, "caption": "Affaccio", "urls": {"small": "https://pwm.im-cdn.it/image/998928980/xxs-c.jpg"}}], "virtualTours": [], "hasMultimedia": true}, "photo": {"id": 998928928, "caption": "Salone", "urls": {"thumb": null, "small": "https://pwm.im-cdn.it/image/998928928/xxs-c.jpg", "medium": null, "large": null}}, "price": {"minValue": null, "maxValue": null, "value": 970000, "formattedValue": "\u20ac 970.000", "formattedValueTop": "\u20ac 970.000", "visible": true, "loweredPrice": null}, "rooms": "4", "shop": null, "surface": "145 m\u00b2", "surfaceValue": "145 m\u00b2", "typology": {"id": 14, "name": "Appartamento"}, "location": {"latitude": 45.4666, "longitude": 9.14839, "marker": "marker"}}], "propertiesCount": null, "saved": null, "title": "Quadrilocale via Trivulzio, De Angeli, Milano", "type": "ad", "typology": {"id": 14, "name": "Appartamento"}, "visibility": "premium"}, "seo": {"anchor": "Quadrilocale via Trivulzio, De Angeli, Milano", "title": "Quadrilocale via Trivulzio, Milano", "metaTitle": "Vendita Appartamento Milano. Quadrilocale in via Trivulzio. Ottimo stato, quarto piano, riscaldamento autonomo, rif. 84693776", "url": "https://www.immobiliare.it/annunci/84693776/"}}, {"realEstate": {"advertiser": {"agency": {"id": 220082, "type": "agency", "label": "agenzia", "displayName": "Five Stars", "imageUrls": {"small": "https://pic.im-cdn.it/imagenoresize/645648160.jpg", "large": "https://pic.im-cdn.it/imagenoresize/645648162.jpg"}, "agencyUrl": "https://www.immobiliare.it/agenzie-immobiliari/220082/five-stars/", "phones": [{"type": "tel1", "value": "02 3669 7559"}, {"type": "cell", "value": "338 997 2044"}], "isPaid": true, "customType": null, "externalLinks": null, "text": null, "track": null, "guaranteed": null}, "supervisor": null, "hasCallNumbers": true}, "contract": "sale", "id": 84013078, "isNew": false, "luxury": true, "price": {"minValue": null, "maxValue": null, "value": 2250000, "formattedValue": "\u20ac 2.250.000", "formattedValueTop": "\u20ac 2.250.000", "visible": true, "loweredPrice": null}, "properties": [{"auction": null, "bathrooms": "3+", "caption": "PENTHOUSE DE ANGELI", "category": {"id": 1, "name": "Residenziale"}, "description": "Agenzia immobilare specializzata nel settore del lusso propone in vendita un attico e super attico in via privata della zona de Angeli di Milano.\nL'esclusivo appartamento che se nello stile pu\u00f2 necessitare di un dolce ammordernamento ,rappresenta un immobile unico e prestigiosissimo per dimensioni ,vista ,e luminosit\u00e0 ,imparagonabili a qualsiasi altro immobile.\nin palazzo di alta rappresentanza si vende ultimo piano luminosissimo per la presenza di ampie porte finestre che corrono su tutto il perimetro.l attico \u00e8 dotato di 5 camere con bagno en suites ovviamente presenti area servit\u00f9 lavanderia e spaziosissima cucina . \n .", "floor": {"abbreviation": "8", "value": "8\u00b0, con ascensore"}, "multimedia": {"photos": [{"id": 991961678, "caption": "foto", "urls": {"small": "https://pwm.im-cdn.it/image/991961678/xxs-c.jpg"}}, {"id": 991960534, "caption": "foto", "urls": {"small": "https://pwm.im-cdn.it/image/991960534/xxs-c.jpg"}}, {"id": 991961274, "caption": "foto", "urls": {"small": "https://pwm.im-cdn.it/image/991961274/xxs-c.jpg"}}, {"id": 991960024, "caption": "foto", "urls": {"small": "https://pwm.im-cdn.it/image/991960024/xxs-c.jpg"}}, {"id": 991963670, "caption": "foto", "urls": {"small": "https://pwm.im-cdn.it/image/991963670/xxs-c.jpg"}}, {"id": 991964776, "caption": "foto", "urls": {"small": "https://pwm.im-cdn.it/image/991964776/xxs-c.jpg"}}, {"id": 991967498, "caption": "foto", "urls": {"small": "https://pwm.im-cdn.it/image/991967498/xxs-c.jpg"}}, {"id": 991972912, "caption": "foto", "urls": {"small": "https://pwm.im-cdn.it/image/991972912/xxs-c.jpg"}}, {"id": 991974028, "caption": "foto", "urls": {"small": "https://pwm.im-cdn.it/image/991974028/xxs-c.jpg"}}, {"id": 991974492, "caption": "foto", "urls": {"small": "https://pwm.im-cdn.it/image/991974492/xxs-c.jpg"}}], "virtualTours": [], "hasMultimedia": true}, "photo": {"id": 991961678, "caption": "foto", "urls": {"thumb": null, "small": "https://pwm.im-cdn.it/image/991961678/xxs-c.jpg", "medium": null, "large": null}}, "price": {"minValue": null, "maxValue": null, "value": 2250000, "formattedValue": "\u20ac 2.250.000", "formattedValueTop": "\u20ac 2.250.000", "visible": true, "loweredPrice": null}, "rooms": "5+", "shop": null, "surface": "275 m\u00b2", "surfaceValue": "275 m\u00b2", "typology": {"id": 15, "name": "Attico"}, "location": {"latitude": 45.465, "longitude": 9.1503, "marker": "marker"}}], "propertiesCount": null, "saved": null, "title": "Attico via Giuseppe Frua 12, Frua, Milano", "type": "ad", "typology": {"id": 15, "name": "Attico"}, "visibility": "premium"}, "seo": {"anchor": "Attico via Giuseppe Frua 12, Frua, Milano", "title": "Attico via Giuseppe Frua 12, Milano", "metaTitle": "Vendita Attico  in via Giuseppe Frua 12 Milano. Ottimo stato, posto auto, terrazza, rif. 84013078", "url": "https://www.immobiliare.it/annunci/84013078/"}}, {"realEstate": {"advertiser": {"agency": {"id": 115853, "type": "agency", "label": "agenzia", "displayName": "RESYSTEMS SRL", "imageUrls": {"small": "https://pic.im-cdn.it/imagenoresize/1108173106.jpg", "large": "https://pic.im-cdn.it/imagenoresize/1108173108.jpg"}, "agencyUrl": "https://www.immobiliare.it/agenzie-immobiliari/115853/resystems-milano/", "phones": [{"type": "vTel1", "value": "02 3540 6534"}], "isPaid": true, "customType": null, "externalLinks": null, "text": null, "track": null, "guaranteed": null}, "supervisor": null, "hasCallNumbers": true}, "contract": "sale", "id": 88791269, "isNew": false, "luxury": false, "price": {"minValue": null, "maxValue": null, "value": 249000, "formattedValue": "\u20ac 249.000", "formattedValueTop": "\u20ac 249.000", "visible": true, "loweredPrice": null}, "properties": [{"auction": null, "bathrooms": "1", "caption": "MILANO WASHINGTON: ATTICO ARREDATO, FINITURE PREGIATE", "category": {"id": 1, "name": "Residenziale"}, "description": "MILANO WASHINGTON: ReSystems Srl propone in vendita all'interno di una delle zone pi\u00f9 ricercate ed esclusive di Milano, un luminosissimo appartamento posto al sesto ed ultimo piano in elegante stabile servito da portineria ed ascensore.\nL'immobile si sviluppa su una superficie di mq 40 composta da comodo open space oltre servizio ed \u00e8 completo di balcone e cantina.\nL'immobile si presenta in perfette condizioni generali con lussuose finiture ed arredato.OTTIMO ANCHE PER INVESITMENTO!Maggiori informazioni al numero di telefono fisso: 02.83421228Seguici sui nostri canali Social:\n- facebook: RESYSTEMSMILANO\n- instagram: resystems_srlVisita il nostro sito web per ulteriori proposte: www.resystems.it", "floor": {"abbreviation": "6", "value": "6\u00b0, con ascensore"}, "multimedia": {"photos": [{"id": 1161822588, "caption": "planimetria", "urls": {"small": "https://pwm.im-cdn.it/image/1161822588/xxs-c.jpg"}}, {"id": 1065937849, "caption": "zona", "urls": {"small": "https://pwm.im-cdn.it/image/1065937849/xxs-c.jpg"}}, {"id": 1065937855, "caption": "zona", "urls": {"small": "https://pwm.im-cdn.it/image/1065937855/xxs-c.jpg"}}, {"id": 1065937867, "caption": "zona", "urls": {"small": "https://pwm.im-cdn.it/image/1065937867/xxs-c.jpg"}}, {"id": 1065937885, "caption": "zona", "urls": {"small": "https://pwm.im-cdn.it/image/1065937885/xxs-c.jpg"}}, {"id": 1065937891, "caption": "zona", "urls": {"small": "https://pwm.im-cdn.it/image/1065937891/xxs-c.jpg"}}, {"id": 1065937903, "caption": "zona", "urls": {"small": "https://pwm.im-cdn.it/image/1065937903/xxs-c.jpg"}}, {"id": 1065937909, "caption": "zona", "urls": {"small": "https://pwm.im-cdn.it/image/1065937909/xxs-c.jpg"}}, {"id": 1065937919, "caption": "zona", "urls": {"small": "https://pwm.im-cdn.it/image/1065937919/xxs-c.jpg"}}, {"id": 1065937931, "caption": "zona", "urls": {"small": "https://pwm.im-cdn.it/image/1065937931/xxs-c.jpg"}}, {"id": 1065937939, "caption": "zona", "urls": {"small": "https://pwm.im-cdn.it/image/1065937939/xxs-c.jpg"}}, {"id": 1065937957, "caption": "zona", "urls": {"small": "https://pwm.im-cdn.it/image/1065937957/xxs-c.jpg"}}, {"id": 1065937961, "caption": "zona", "urls": {"small": "https://pwm.im-cdn.it/image/1065937961/xxs-c.jpg"}}, {"id": 1065937973, "caption": "zona", "urls": {"small": "https://pwm.im-cdn.it/image/1065937973/xxs-c.jpg"}}, {"id": 1065937985, "caption": "zona", "urls": {"small": "https://pwm.im-cdn.it/image/1065937985/xxs-c.jpg"}}, {"id": 1065937841, "caption": "zona", "urls": {"small": "https://pwm.im-cdn.it/image/1065937841/xxs-c.jpg"}}, {"id": 1065937991, "caption": "zona", "urls": {"small": "https://pwm.im-cdn.it/image/1065937991/xxs-c.jpg"}}], "virtualTours": [null], "hasMultimedia": true}, "photo": {"id": 1161822588, "caption": "planimetria", "urls": {"thumb": null, "small": "https://pwm.im-cdn.it/image/1161822588/xxs-c.jpg", "medium": null, "large": null}}, "price": {"minValue": null, "maxValue": null, "value": 249000, "formattedValue": "\u20ac 249.000", "formattedValueTop": "\u20ac 249.000", "visible": true, "loweredPrice": null}, "rooms": "1", "shop": null, "surface": "40 m\u00b2", "surfaceValue": "40 m\u00b2", "typology": {"id": 15, "name": "Attico"}, "location": {"latitude": 45.4621, "longitude": 9.1514, "marker": "marker"}}], "propertiesCount": null, "saved": null, "title": "Attico via Sardegna 45, Washington, Milano", "type": "ad", "typology": {"id": 15, "name": "Attico"}, "visibility": "premium"}, "seo": {"anchor": "Attico via Sardegna 45, Washington, Milano", "title": "Attico via Sardegna 45, Milano", "metaTitle": "Vendita Attico  in via Sardegna 45 Milano. Ottimo stato, balcone, rif. 88791269", "url": "https://www.immobiliare.it/annunci/88791269/"}}, {"realEstate": {"advertiser": {"agency": {"id": 34137, "type": "agency", "label": "agenzia", "displayName": "Cavour Immobiliare", "imageUrls": {"small": "https://pic.im-cdn.it/imagenoresize/162239806.jpg", "large": "https://pic.im-cdn.it/imagenoresize/162239814.jpg"}, "agencyUrl": "https://www.immobiliare.it/agenzie-immobiliari/34137/cavour-milano/", "phones": [{"type": "tel1", "value": "02 3598 1509"}], "isPaid": true, "customType": null, "externalLinks": null, "text": null, "track": null, "guaranteed": null}, "supervisor": null, "hasCallNumbers": true}, "contract": "sale", "id": 78812025, "isNew": false, "luxury": true, "price": {"minValue": null, "maxValue": null, "value": 2250000, "formattedValue": "\u20ac 2.250.000", "formattedValueTop": "\u20ac 2.250.000", "visible": true, "loweredPrice": null}, "properties": [{"auction": null, "bathrooms": "3+", "caption": "Luminoso attico con terrazza", "category": {"id": 1, "name": "Residenziale"}, "description": "In contesto moderno dotato di 3 ascensori e servizio di portierato splendido attico dalle caratteristiche uniche. Al piano ottavo vi sono i doppi ingressi: quello padronale che apre al soggiorno doppio con la sala da pranzo e una maestosa cucina di oltre 20 mq e quello di servizio dal quale si accede alla camera di servizio/Lavanderia. La zona notte \u00e8 composta da 3 camere da letto e tripli servizi. Un'elegante scala disposta nel soggiorno porta al piano superiore dove vi \u00e8 una camera da letto, uno studio e un suggestivo terrazzino sfruttabile per mangiare godendosi la vista dello Skyline milanese.\nOltre al terrazzo vi sono ampie balconate grazie alle quali questa abitazione, da ristrutturare, gode di una spiccata luminosit\u00e0 in tutti i suoi ambienti e in qualsiasi ora della giornata.\nComple", "floor": {"abbreviation": "8", "value": "8\u00b0, con ascensore"}, "multimedia": {"photos": [{"id": 893397933, "caption": "Soggiorno", "urls": {"small": "https://pwm.im-cdn.it/image/893397933/xxs-c.jpg"}}, {"id": 893397955, "caption": "Soggiorno", "urls": {"small": "https://pwm.im-cdn.it/image/893397955/xxs-c.jpg"}}, {"id": 893397943, "caption": "Sogg-Cucina", "urls": {"small": "https://pwm.im-cdn.it/image/893397943/xxs-c.jpg"}}, {"id": 893397897, "caption": "Cucina Sogg", "urls": {"small": "https://pwm.im-cdn.it/image/893397897/xxs-c.jpg"}}, {"id": 893397907, "caption": "Cucina", "urls": {"small": "https://pwm.im-cdn.it/image/893397907/xxs-c.jpg"}}, {"id": 893397925, "caption": "Spazio pranzo", "urls": {"small": "https://pwm.im-cdn.it/image/893397925/xxs-c.jpg"}}, {"id": 893397885, "caption": "Camera", "urls": {"small": "https://pwm.im-cdn.it/image/893397885/xxs-c.jpg"}}, {"id": 893397873, "caption": "Camera", "urls": {"small": "https://pwm.im-cdn.it/image/893397873/xxs-c.jpg"}}, {"id": 893397915, "caption": "Camera servizio - Lavand", "urls": {"small": "https://pwm.im-cdn.it/image/893397915/xxs-c.jpg"}}, {"id": 893397861, "caption": "Bagno", "urls": {"small": "https://pwm.im-cdn.it/image/893397861/xxs-c.jpg"}}, {"id": 893397965, "caption": "Terrazza", "urls": {"small": "https://pwm.im-cdn.it/image/893397965/xxs-c.jpg"}}, {"id": 893397977, "caption": "Vista esterna", "urls": {"small": "https://pwm.im-cdn.it/image/893397977/xxs-c.jpg"}}], "virtualTours": [], "hasMultimedia": true}, "photo": {"id": 893397933, "caption": "Soggiorno", "urls": {"thumb": null, "small": "https://pwm.im-cdn.it/image/893397933/xxs-c.jpg", "medium": null, "large": null}}, "price": {"minValue": null, "maxValue": null, "value": 2250000, "formattedValue": "\u20ac 2.250.000", "formattedValueTop": "\u20ac 2.250.000", "visible": true, "loweredPrice": null}, "rooms": "5+", "shop": null, "surface": "260 m\u00b2", "surfaceValue": "260 m\u00b2", "typology": {"id": 14, "name": "Appartamento"}, "location": {"latitude": 45.4643, "longitude": 9.1514, "marker": "marker"}}], "propertiesCount": null, "saved": null, "title": "Appartamento via Farnese 1, Frua, Milano", "type": "ad", "typology": {"id": 14, "name": "Appartamento"}, "visibility": "supervetrina"}, "seo": {"anchor": "Appartamento via Farnese 1, Frua, Milano", "title": "Appartamento via Farnese 1, Milano", "metaTitle": "Vendita Appartamento  in via Farnese 1. Milano, rif. 78812025", "url": "https://www.immobiliare.it/annunci/78812025/"}}, {"realEstate": {"advertiser": {"agency": {"id": 122569, "type": "agency", "label": "agenzia", "displayName": "MONTI32 Immobili", "imageUrls": {"small": "https://pic.im-cdn.it/imagenoresize/240587750.jpg", "large": "https://pic.im-cdn.it/imagenoresize/240587753.jpg"}, "agencyUrl": "https://www.immobiliare.it/agenzie-immobiliari/122569/monti/", "phones": [{"type": "tel1", "value": "02 498 4412"}], "isPaid": true, "customType": null, "externalLinks": null, "text": null, "track": null, "guaranteed": null}, "supervisor": null, "hasCallNumbers": true}, "contract": "sale", "id": 78704651, "isNew": false, "luxury": false, "price": {"minValue": null, "maxValue": null, "value": 450000, "formattedValue": "\u20ac 450.000", "formattedValueTop": "\u20ac 450.000", "visible": true, "loweredPrice": null}, "properties": [{"auction": null, "bathrooms": "1", "caption": "Loft Openspace MM De Angeli", "category": {"id": 1, "name": "Residenziale"}, "description": "Via Frua \u2013 MM De Angeli. In signorile contesto anni 70 con servizio di portineria, silenzioso loft openspace di 133 mq al piano semi interrato accatastato A/2 abitazione, in esposizione interna con affaccio sui giardini condominiali, composto da due ingressi, uno dalla scala condominiale ed uno indipendente dal giardino, cucina a vista e bagno. Da personalizzare. Riscaldamento centralizzato. Possibilit\u00e0 posto auto. Prezzo \u20ac 450.000,00. Certificazione energetica G \u2013 175 kWh/mqa. Per informazioni tel. 024984412 Monti32 Immobili www.monti32.it", "floor": {"abbreviation": "S", "value": "Seminterrato, con ascensore"}, "multimedia": {"photos": [{"id": 999145830, "caption": "contesto", "urls": {"small": "https://pwm.im-cdn.it/image/999145830/xxs-c.jpg"}}, {"id": 999145820, "caption": "contesto", "urls": {"small": "https://pwm.im-cdn.it/image/999145820/xxs-c.jpg"}}, {"id": 999145810, "caption": "cucina", "urls": {"small": "https://pwm.im-cdn.it/image/999145810/xxs-c.jpg"}}, {"id": 999145838, "caption": "loft", "urls": {"small": "https://pwm.im-cdn.it/image/999145838/xxs-c.jpg"}}, {"id": 999145846, "caption": "loft", "urls": {"small": "https://pwm.im-cdn.it/image/999145846/xxs-c.jpg"}}, {"id": 999145850, "caption": "loft", "urls": {"small": "https://pwm.im-cdn.it/image/999145850/xxs-c.jpg"}}, {"id": 999145856, "caption": "contesto", "urls": {"small": "https://pwm.im-cdn.it/image/999145856/xxs-c.jpg"}}, {"id": 999145864, "caption": "lofy", "urls": {"small": "https://pwm.im-cdn.it/image/999145864/xxs-c.jpg"}}, {"id": 999145870, "caption": "bagno", "urls": {"small": "https://pwm.im-cdn.it/image/999145870/xxs-c.jpg"}}, {"id": 999145876, "caption": "contesto", "urls": {"small": "https://pwm.im-cdn.it/image/999145876/xxs-c.jpg"}}, {"id": 999145884, "caption": "contesto", "urls": {"small": "https://pwm.im-cdn.it/image/999145884/xxs-c.jpg"}}, {"id": 999145892, "caption": "contesto", "urls": {"small": "https://pwm.im-cdn.it/image/999145892/xxs-c.jpg"}}, {"id": 999145902, "caption": "loft", "urls": {"small": "https://pwm.im-cdn.it/image/999145902/xxs-c.jpg"}}, {"id": 999145910, "caption": "cucina", "urls": {"small": "https://pwm.im-cdn.it/image/999145910/xxs-c.jpg"}}, {"id": 999145918, "caption": "loft", "urls": {"small": "https://pwm.im-cdn.it/image/999145918/xxs-c.jpg"}}, {"id": 999145924, "caption": "loft", "urls": {"small": "https://pwm.im-cdn.it/image/999145924/xxs-c.jpg"}}, {"id": 999145934, "caption": "contesto", "urls": {"small": "https://pwm.im-cdn.it/image/999145934/xxs-c.jpg"}}, {"id": 999145942, "caption": "loft", "urls": {"small": "https://pwm.im-cdn.it/image/999145942/xxs-c.jpg"}}, {"id": 999145950, "caption": "bagno", "urls": {"small": "https://pwm.im-cdn.it/image/999145950/xxs-c.jpg"}}, {"id": 999145956, "caption": "contesto", "urls": {"small": "https://pwm.im-cdn.it/image/999145956/xxs-c.jpg"}}], "virtualTours": [], "hasMultimedia": true}, "photo": {"id": 999145830, "caption": "contesto", "urls": {"thumb": null, "small": "https://pwm.im-cdn.it/image/999145830/xxs-c.jpg", "medium": null, "large": null}}, "price": {"minValue": null, "maxValue": null, "value": 450000, "formattedValue": "\u20ac 450.000", "formattedValueTop": "\u20ac 450.000", "visible": true, "loweredPrice": null}, "rooms": "1", "shop": null, "surface": "133 m\u00b2", "surfaceValue": "133 m\u00b2", "typology": {"id": 17, "name": "Loft"}, "location": {"latitude": 45.4651, "longitude": 9.1518, "marker": "marker"}}], "propertiesCount": null, "saved": null, "title": "Loft via Giuseppe Frua, Frua, Milano", "type": "ad", "typology": {"id": 17, "name": "Loft"}, "visibility": "premium"}, "seo": {"anchor": "Loft via Giuseppe Frua, Frua, Milano", "title": "Loft via Giuseppe Frua, Milano", "metaTitle": "Vendita Loft  in via Giuseppe Frua Milano. Buono stato, riscaldamento centralizzato, 133 mq, rif. 78704651", "url": "https://www.immobiliare.it/annunci/78704651/"}}, {"realEstate": {"advertiser": {"agency": {"id": 163778, "type": "agency", "label": "agenzia", "displayName": "Domus Futura", "imageUrls": {"small": "https://pic.im-cdn.it/imagenoresize/315807308.jpg", "large": "https://pic.im-cdn.it/imagenoresize/315807310.jpg"}, "agencyUrl": "https://www.immobiliare.it/agenzie-immobiliari/163778/domus-futura-milano/", "phones": [{"type": "vTel1", "value": "02 9475 9049"}], "isPaid": true, "customType": null, "externalLinks": null, "text": null, "track": null, "guaranteed": null}, "supervisor": null, "hasCallNumbers": true}, "contract": "sale", "id": 73863528, "isNew": false, "luxury": false, "price": {"minValue": null, "maxValue": null, "value": 400000, "formattedValue": "\u20ac 400.000", "formattedValueTop": "\u20ac 400.000", "visible": true, "loweredPrice": null}, "properties": [{"auction": null, "bathrooms": "1", "caption": "via washington bilocale", "category": {"id": 1, "name": "Residenziale"}, "description": "Rif: VIA WASHINGTON, stabile signorile, grazioso bilocale di 60 mq, soggiorno con cucina a vista, camera da letto, 1 bagno. Prezzo: \u20ac 400.000. Per info telefonare al ( 333.6215518 ).", "floor": {"abbreviation": "2", "value": "2\u00b0, con ascensore"}, "multimedia": {"photos": [{"id": 1052472088, "caption": "0", "urls": {"small": "https://pwm.im-cdn.it/image/1052472088/xxs-c.jpg"}}, {"id": 1052472104, "caption": "IMG_0177", "urls": {"small": "https://pwm.im-cdn.it/image/1052472104/xxs-c.jpg"}}, {"id": 1052472118, "caption": "IMG_0179", "urls": {"small": "https://pwm.im-cdn.it/image/1052472118/xxs-c.jpg"}}, {"id": 1052472132, "caption": "IMG_7075", "urls": {"small": "https://pwm.im-cdn.it/image/1052472132/xxs-c.jpg"}}], "virtualTours": [], "hasMultimedia": true}, "photo": {"id": 1052472088, "caption": "0", "urls": {"thumb": null, "small": "https://pwm.im-cdn.it/image/1052472088/xxs-c.jpg", "medium": null, "large": null}}, "price": {"minValue": null, "maxValue": null, "value": 400000, "formattedValue": "\u20ac 400.000", "formattedValueTop": "\u20ac 400.000", "visible": true, "loweredPrice": null}, "rooms": "2", "shop": null, "surface": "60 m\u00b2", "surfaceValue": "60 m\u00b2", "typology": {"id": 14, "name": "Appartamento"}, "location": {"latitude": 45.4658, "longitude": 9.1549, "marker": "marker"}}], "propertiesCount": null, "saved": null, "title": "Bilocale via washington, Washington, Milano", "type": "ad", "typology": {"id": 14, "name": "Appartamento"}, "visibility": "premium"}, "seo": {"anchor": "Bilocale via washington, Washington, Milano", "title": "Bilocale via washington, Milano", "metaTitle": "Vendita Appartamento Milano. Bilocale in via washington. Buono stato, primo piano, riscaldamento centralizzato, rif. 73863528", "url": "https://www.immobiliare.it/annunci/73863528/"}}], "breadcrumbs": [{"label": "Immobiliare.it", "link": {"url": "https://www.immobiliare.it/"}}, {"label": "Provincia di Milano", "link": {"url": "https://www.immobiliare.it/vendita-case/milano-provincia/"}, "type": "provincia"}, {"label": "Milano", "link": {"url": "https://www.immobiliare.it/vendita-case/milano/"}, "type": "comune"}, {"label": "Solari, Washington", "links": null, "link": {"url": "https://www.immobiliare.it/vendita-case/milano/solari-washington/"}, "type": "zona"}, {"label": "Frua", "link": {"url": "https://www.immobiliare.it/vendita-case/milano/frua/"}, "type": "quartiere", "items": [{"label": "Dezza", "title": " Dezza", "link": {"url": "https://www.immobiliare.it/vendita-case/milano/dezza/", "follow": true, "current": false}}, {"label": "Frua", "title": " Frua", "link": {"url": "https://www.immobiliare.it/vendita-case/milano/frua/", "follow": true, "current": true}}, {"label": "Solari", "title": " Solari", "link": {"url": "https://www.immobiliare.it/vendita-case/milano/solari/", "follow": true, "current": false}}, {"label": "Vercelli - Wagner", "title": " Vercelli - Wagner", "link": {"url": "https://www.immobiliare.it/vendita-case/milano/vercelli-wagner/", "follow": true, "current": false}}, {"label": "Washington", "title": " Washington", "link": {"url": "https://www.immobiliare.it/vendita-case/milano/washington/", "follow": true, "current": false}}]}], "agencies": [], "seoData": {"title": "Case in vendita in zona Frua, Milano - Pag. 4 - Immobiliare.it", "subtitle": "case in vendita zona Frua a Milano", "description": "81 annunci di case in vendita a Frua, Milano da 190.000 euro. Scopri tutti gli annunci privati e di agenzie e scegli con Immobiliare.it la tua futura casa.", "searchName": "Case in vendita a Milano", "facebookSettings": {"prefix": "", "title": "Case in vendita in zona Frua, Milano - Pag. 4 - Immobiliare.it", "description": "81 annunci di case in vendita a Frua, Milano da 190.000 euro. Scopri tutti gli annunci privati e di agenzie e scegli con Immobiliare.it la tua futura casa.", "image": "", "subtitle": "case in vendita zona Frua a Milano"}, "robots": "noindex,follow", "alternate": [{"rel": "alternate", "hreflang": "en", "href": "https://www.immobiliare.it/en/vendita-case/milano/frua/?pag=4"}, {"rel": "alternate", "hreflang": "de", "href": "https://www.immobiliare.it/de/vendita-case/milano/frua/?pag=4"}, {"rel": "alternate", "hreflang": "es", "href": "https://www.immobiliare.it/es/vendita-case/milano/frua/?pag=4"}, {"rel": "alternate", "hreflang": "fr", "href": "https://www.immobiliare.it/fr/vendita-case/milano/frua/?pag=4"}, {"rel": "alternate", "hreflang": "el", "href": "https://www.immobiliare.it/el/vendita-case/milano/frua/?pag=4"}, {"rel": "alternate", "hreflang": "pt", "href": "https://www.immobiliare.it/pt/vendita-case/milano/frua/?pag=4"}, {"rel": "alternate", "hreflang": "ru", "href": "https://www.immobiliare.it/ru/vendita-case/milano/frua/?pag=4"}, {"rel": "alternate", "hreflang": "it", "href": "https://www.immobiliare.it/vendita-case/milano/frua/?pag=4"}, {"rel": "alternate", "hreflang": "x-default", "href": "https://www.immobiliare.it/vendita-case/milano/frua/?pag=4"}], "canonical": "https://www.immobiliare.it/vendita-case/milano/frua/?pag=4", "appleItunesApp": {"appId": 335948517, "affiliateData": "ct=Smart-banner-safari&pt=304468", "appArgument": "immogrp2://urlrev=2"}, "prevPage": "https://www.immobiliare.it/vendita-case/milano/frua/?pag=3", "nextPage": null}, "relatedSearches": {"title": "Annunci immobiliari Frua", "data": [{"type": "feature-group", "titleList": "Case in vendita a Frua con:", "data": [{"text": "ascensore", "link": {"url": "https://www.immobiliare.it/vendita-case/milano/frua/con-ascensore/"}}, {"text": "garage", "link": {"url": "https://www.immobiliare.it/vendita-case/milano/frua/con-garage/"}}, {"text": "cantina", "link": {"url": "https://www.immobiliare.it/vendita-case/milano/frua/con-cantina/"}}, {"text": "terrazzo", "link": {"url": "https://www.immobiliare.it/vendita-case/milano/frua/con-terrazzo/"}}, {"text": "giardino", "link": {"url": "https://www.immobiliare.it/vendita-case/milano/frua/con-giardino/"}}, {"text": "piano terra", "link": {"url": "https://www.immobiliare.it/vendita-case/milano/frua/con-piano-terra/"}}, {"text": "piani intermedi", "link": {"url": "https://www.immobiliare.it/vendita-case/milano/frua/con-piani-intermedi/"}}, {"text": "riscaldamento autonomo", "link": {"url": "https://www.immobiliare.it/vendita-case/milano/frua/con-riscaldamento-autonomo/"}}, {"text": "aria condizionata", "link": {"url": "https://www.immobiliare.it/vendita-case/milano/frua/con-aria-condizionata/"}}]}, {"titleList": "Ricerche correlate", "data": [{"text": "agenzie immobiliari Milano", "link": {"url": "https://www.immobiliare.it/agenzie-immobiliari/milano/"}}, {"text": "prezzi case", "link": {"url": "https://www.immobiliare.it/mercato-immobiliare/lombardia/milano/solari-washington/"}}, {"text": "case di lusso", "link": {"url": "https://www.immobiliare.it/vendita-case/milano/frua/con-lusso/"}}]}]}, "suggestedSearchData": {"token": "a2031ee5d2342485682a793ff9829ba1", "verticaleSito": "annunci_residenziali"}, "currentPage": 4, "maxPages": 4}