{"count": 29, "totalAds": 29, "isResultsLimitReached": false, "results": [{"realEstate": {"advertiser": {"agency": {"id": 142837, "type": "agency", "label": "agenzia", "displayName": "Affiliato Tecnocasa: STUDIO PIAZZA UDINE SNC", "imageUrls": {"small": "https://pic.im-cdn.it/imagenoresize/1160062428.jpg", "large": "https://pic.im-cdn.it/imagenoresize/1160062430.jpg"}, "agencyUrl": "https://www.immobiliare.it/agenzie-immobiliari/142837/tecnocasa-milano-crescenzago/", "phones": [{"type": "vTel1", "value": "02 8295 4349"}], "isPaid": true, "customType": "tecnomedia", "externalLinks": null, "text": null, "track": null, "guaranteed": false}, "supervisor": null, "hasCallNumbers": true}, "contract": "sale", "id": 91544696, "isNew": false, "luxury": false, "price": {"minValue": null, "maxValue": null, "value": 335000, "formattedValue": "\u20ac 335.000", "formattedValueTop": "\u20ac 335.000", "visible": true, "loweredPrice": null}, "properties": [{"auction": null, "bathrooms": "2", "caption": "Q.re Feltre, trilocale completamente ristrutturato", "category": {"id": 1, "name": "Residenziale"}, "description": "Quartiere Feltre-via Crescenzago, a pochissimi passi da tutti i servizi che la zona offre, con supermercato, bar, farmacia, ufficio postale sotto casa, proponiamo trilocale con doppi servizi.\n \nL'appartamento si trova in uno stabile degli anni '60 di soli tre piani, ed \u00e8 ubicato a 600 metri dalla metropolitana di Udine e 600 metri dalla stazione di Lambrate, in zona comodissima per l'accesso alla tangenziale Est.L'immobile \u00e8 stato completamente ristrutturato nel 2015 con pavimentazione in gres porcellanato, aria condizionata, infissi in legno e doppi vetri, tapparelle elettriche, zanzariere, impianto di allarme. Internamente \u00e8 composto da un ampio ingresso, soggiorno, cucina abitabile, due camere da letto (di cui una con cabina armadio), doppi servizi e due balconi.L'appartamento gode di u", "floor": {"abbreviation": "R", "value": "Piano rialzato, con ascensore"}, "multimedia": {"photos": [{"id": 1108964028, "caption": "Soggiorno", "urls": {"small": "https://pic.im-cdn.it/image/1108964028/xxs-c.jpg"}}, {"id": 1108964030, "caption": "Soggiorno", "urls": {"small": "https://pic.im-cdn.it/image/1108964030/xxs-c.jpg"}}, {"id": 1108964034, "caption": "Cucina", "urls": {"small": "https://pic.im-cdn.it/image/1108964034/xxs-c.jpg"}}, {"id": 1108964038, "caption": "Cucina", "urls": {"small": "https://pic.im-cdn.it/image/1108964038/xxs-c.jpg"}}, {"id": 1108964040, "caption": "Cucina", "urls": {"small": "https://pic.im-cdn.it/image/1108964040/xxs-c.jpg"}}, {"id": 1108964044, "caption": "Camera", "urls": {"small": "https://pic.im-cdn.it/image/1108964044/xxs-c.jpg"}}, {"id": 1108964046, "caption": "Camera", "urls": {"small": "https://pic.im-cdn.it/image/1108964046/xxs-c.jpg"}}, {"id": 1108964048, "caption": "Camera", "urls": {"small": "https://pic.im-cdn.it/image/1108964048/xxs-c.jpg"}}, {"id": 1108964052, "caption": "Bagno", "urls": {"small": "https://pic.im-cdn.it/image/1108964052/xxs-c.jpg"}}, {"id": 1108964054, "caption": "Bagno", "urls": {"small": "https://pic.im-cdn.it/image/1108964054/xxs-c.jpg"}}, {"id": 1108964056, "caption": "Bagno", "urls": {"small": "https://pic.im-cdn.it/image/1108964056/xxs-c.jpg"}}, {"id": 1108964060, "caption": "Camera", "urls": {"small": "https://pic.im-cdn.it/image/1108964060/xxs-c.jpg"}}, {"id": 1108964062, "caption": "Camera", "urls": {"small": "https://pic.im-cdn.it/image/1108964062/xxs-c.jpg"}}, {"id": 1108964066, "caption": "Bagno", "urls": {"small": "https://pic.im-cdn.it/image/1108964066/xxs-c.jpg"}}, {"id": 1109008826, "caption": "Piantina", "urls": {"small": "https://pic.im-cdn.it/image/1109008826/xxs-c.jpg"}}], "virtualTours": [], "hasMultimedia": true}, "photo": {"id": 1108964028, "caption": "Soggiorno", "urls": {"thumb": null, "small": "https://pic.im-cdn.it/image/1108964028/xxs-c.jpg", "medium": null, "large": null}}, "price": {"minValue": null, "maxValue": null, "value": 335000, "formattedValue": "\u20ac 335.000", "formattedValueTop": "\u20ac 335.000", "visible": true, "loweredPrice": null}, "rooms": "3", "shop": null, "surface": "90 m\u00b2", "surfaceValue": "90 m\u00b2", "typology": {"id": 14, "name": "Appartamento"}, "location": {"latitude": 45.4881, "longitude": 9.2422, "marker": "marker"}}], "propertiesCount": null, "saved": null, "title": "Trilocale via Crescenzago 24, Quartiere Feltre, Milano", "type": "ad", "typology": {"id": 14, "name": "Appartamento"}, "visibility": "premium"}, "seo": {"anchor": "Trilocale via Crescenzago 24, Quartiere Feltre, Milano", "title": "Trilocale via Crescenzago 24, Milano", "metaTitle": "Vendita Appartamento Milano. Trilocale in via Crescenzago 24. Ottimo stato, piano rialzato, balcone, riscaldamento centralizzato, rif. 91544696", "url": "https://www.immobiliare.it/annunci/91544696/"}}, {"realEstate": {"advertiser": {"agency": {"id": 65294, "type": "agency", "label": "agenzia", "displayName": "Tecnoimmobiliare", "imageUrls": null, "agencyUrl": "https://www.immobiliare.it/agenzie-immobiliari/65294/tecnoimmobiliare-reggio/", "phones": [{"type": "vTel1", "value": "0522 152 0444"}], "isPaid": true, "customType": null, "externalLinks": null, "text": null, "track": null, "guaranteed": null}, "supervisor": null, "hasCallNumbers": true}, "contract": "sale", "id": 90358951, "isNew": false, "luxury": false, "price": {"minValue": null, "maxValue": null, "value": 1000000, "formattedValue": "\u20ac 1.000.000", "formattedValueTop": "\u20ac 1.000.000", "visible": true, "loweredPrice": null}, "properties": [{"auction": null, "bathrooms": null, "caption": null, "category": {"id": 1, "name": "Residenziale"}, "description": "milano zona lambrate, piccolo complesso immobiliare per demolizione e ricostruzione. mq 730 totali da realizzare in lotto con doppio affaccio, ottimo per usi uffici e abitazione.", "floor": null, "multimedia": {"photos": [{"id": 1122861944, "caption": "5F804349-C4CB-4503-9B5A-D2D8ACB0543D.jpeg", "urls": {"small": "https://pwm.im-cdn.it/image/1122861944/xxs-c.jpg"}}], "virtualTours": [], "hasMultimedia": true}, "photo": {"id": 1122861944, "caption": "5F804349-C4CB-4503-9B5A-D2D8ACB0543D.jpeg", "urls": {"thumb": null, "small": "https://pwm.im-cdn.it/image/1122861944/xxs-c.jpg", "medium": null, "large": null}}, "price": {"minValue": null, "maxValue": null, "value": 1000000, "formattedValue": "\u20ac 1.000.000", "formattedValueTop": "\u20ac 1.000.000", "visible": true, "loweredPrice": null}, "rooms": "5", "shop": null, "surface": "730 m\u00b2", "surfaceValue": "730 m\u00b2", "typology": {"id": 26, "name": "Villa a schiera"}, "location": {"latitude": 45.487, "longitude": 9.24087, "marker": "only_area"}}], "propertiesCount": null, "saved": null, "title": "Villa a schiera 5 locali, da ristrutturare, Quartiere Feltre, Milano", "type": "ad", "typology": {"id": 26, "name": "Villa a schiera"}, "visibility": "premium"}, "seo": {"anchor": "Villa a schiera 5 locali, da ristrutturare, Quartiere Feltre, Milano", "title": "Villa a schiera 5 locali, da ristrutturare, Milano", "metaTitle": "Vendita Villa a schiera  Milano. Da ristrutturare, 730 mq, rif. 90358951", "url": "https://www.immobiliare.it/annunci/90358951/"}}, {"realEstate": {"advertiser": {"agency": {"id": 213012, "type": "agency", "label": "agenzia", "displayName": "Immobiliare Lambrate", "imageUrls": {"small": "https://pic.im-cdn.it/imagenoresize/712717147.jpg", "large": "https://pic.im-cdn.it/imagenoresize/712717149.jpg"}, "agencyUrl": "https://www.immobiliare.it/agenzie-immobiliari/213012/immobiliare-lambrate/", "phones": [{"type": "vTel1", "value": "02 3540 5916"}], "isPaid": true, "customType": null, "externalLinks": null, "text": null, "track": null, "guaranteed": null}, "supervisor": null, "hasCallNumbers": true}, "contract": "sale", "id": 88997847, "isNew": false, "luxury": false, "price": {"minValue": null, "maxValue": null, "value": 173000, "formattedValue": "\u20ac 173.000", "formattedValueTop": "\u20ac 173.000", "visible": true, "loweredPrice": null}, "properties": [{"auction": null, "bathrooms": "1", "caption": "Monolocale in vendita, piano alto, APPROVATO 110 SUPERBONUS", "category": {"id": 1, "name": "Residenziale"}, "description": "Milano, Via Crescenzago 3, proponiamo in vendita ampio monolocale, mq. 45 con bagno e balcone, ristrutturato\nSoggiorno.notte con cucina a vista, bagno finestrato, balcone, cantina. \nL\u2019immobile si trova a Milano in zona Lambrate, a 500 metri dalla Stazione Ferroviaria e Metropolitana di Lambrate, a soli 500 mt dalla fermata dell\u2019autobus 54 (M2 Lambrate/Duomo), 39 (Pitteri/Loreto), 75 (Via Pitteri/M2 Cascina Gobba) e del tram 33 (Rim. ze di Lambrate/P. le Lagosta). Ottima l\u2019ubicazione per la vicinanza alla Tangenziale Est, al supermercato Esselunga ed all\u2019aeroporto di Linate. Riscaldamento autonomo.OTTIMA SOLUZIONE PER INVESTIMENTO\n DISPONIBILIT\u00e0 DI UN IMMOBILE CON LE STESSE CARATTERISTICHE E STABILE, AL PIANO 4 Euro 173.000 A REDDITO!\nAPPROVATA 110 SUPERBONUS!DISPONIBILIT\u00e0 DI UN IMMOBILE CO", "floor": {"abbreviation": "6", "value": "6\u00b0, con ascensore"}, "multimedia": {"photos": [{"id": 1069260449, "caption": "", "urls": {"small": "https://pwm.im-cdn.it/image/1069260449/xxs-c.jpg"}}, {"id": 1069260455, "caption": "", "urls": {"small": "https://pwm.im-cdn.it/image/1069260455/xxs-c.jpg"}}, {"id": 1069260461, "caption": "", "urls": {"small": "https://pwm.im-cdn.it/image/1069260461/xxs-c.jpg"}}, {"id": 1069260465, "caption": "", "urls": {"small": "https://pwm.im-cdn.it/image/1069260465/xxs-c.jpg"}}, {"id": 1069260475, "caption": "", "urls": {"small": "https://pwm.im-cdn.it/image/1069260475/xxs-c.jpg"}}, {"id": 1069260487, "caption": "", "urls": {"small": "https://pwm.im-cdn.it/image/1069260487/xxs-c.jpg"}}, {"id": 1069260501, "caption": "", "urls": {"small": "https://pwm.im-cdn.it/image/1069260501/xxs-c.jpg"}}, {"id": 1069260505, "caption": "", "urls": {"small": "https://pwm.im-cdn.it/image/1069260505/xxs-c.jpg"}}, {"id": 1069260511, "caption": "", "urls": {"small": "https://pwm.im-cdn.it/image/1069260511/xxs-c.jpg"}}, {"id": 1069260539, "caption": "", "urls": {"small": "https://pwm.im-cdn.it/image/1069260539/xxs-c.jpg"}}, {"id": 1069260553, "caption": "", "urls": {"small": "https://pwm.im-cdn.it/image/1069260553/xxs-c.jpg"}}, {"id": 1069260571, "caption": "", "urls": {"small": "https://pwm.im-cdn.it/image/1069260571/xxs-c.jpg"}}, {"id": 1069260583, "caption": "", "urls": {"small": "https://pwm.im-cdn.it/image/1069260583/xxs-c.jpg"}}, {"id": 1069260597, "caption": "", "urls": {"small": "https://pwm.im-cdn.it/image/1069260597/xxs-c.jpg"}}, {"id": 1069260607, "caption": "", "urls": {"small": "https://pwm.im-cdn.it/image/1069260607/xxs-c.jpg"}}, {"id": 1069260613, "caption": "", "urls": {"small": "https://pwm.im-cdn.it/image/1069260613/xxs-c.jpg"}}, {"id": 1069260619, "caption": "", "urls": {"small": "https://pwm.im-cdn.it/image/1069260619/xxs-c.jpg"}}, {"id": 1069260627, "caption": "", "urls": {"small": "https://pwm.im-cdn.it/image/1069260627/xxs-c.jpg"}}, {"id": 1069260637, "caption": "", "urls": {"small": "https://pwm.im-cdn.it/image/1069260637/xxs-c.jpg"}}, {"id": 1069260649, "caption": "", "urls": {"small": "https://pwm.im-cdn.it/image/1069260649/xxs-c.jpg"}}], "virtualTours": [], "hasMultimedia": true}, "photo": {"id": 1069260449, "caption": "", "urls": {"thumb": null, "small": "https://pwm.im-cdn.it/image/1069260449/xxs-c.jpg", "medium": null, "large": null}}, "price": {"minValue": null, "maxValue": null, "value": 173000, "formattedValue": "\u20ac 173.000", "formattedValueTop": "\u20ac 173.000", "visible": true, "loweredPrice": null}, "rooms": "1", "shop": null, "surface": "45 m\u00b2", "surfaceValue": "45 m\u00b2", "typology": {"id": 14, "name": "Appartamento"}, "location": {"latitude": 45.4861, "longitude": 9.2428, "marker": "marker"}}], "propertiesCount": null, "saved": null, "title": "Monolocale via Crescenzago 3, Lambrate, Milano", "type": "ad", "typology": {"id": 14, "name": "Appartamento"}, "visibility": "vetrina"}, "seo": {"anchor": "Monolocale via Crescenzago 3, Lambrate, Milano", "title": "Monolocale via Crescenzago 3, Milano", "metaTitle": "Vendita Appartamento Milano. Monolocale in via Crescenzago 3. Ottimo stato, sesto piano, balcone, riscaldamento centralizzato, rif. 88997847", "url": "https://www.immobiliare.it/annunci/88997847/"}}, {"realEstate": {"advertiser": {"agency": {"id": 238600, "type": "agency", "label": "agenzia", "displayName": "Iconacasa Milano Stazione Centrale", "imageUrls": {"small": "https://pic.im-cdn.it/imagenoresize/776629996.jpg", "large": "https://pic.im-cdn.it/imagenoresize/776629998.jpg"}, "agencyUrl": "https://www.immobiliare.it/agenzie-immobiliari/238600/milano-stazione-centrale/", "phones": [{"type": "vTel1", "value": "02 3540 7061"}], "isPaid": true, "customType": null, "externalLinks": null, "text": null, "track": null, "guaranteed": null}, "supervisor": null, "hasCallNumbers": true}, "contract": "sale", "id": 86462322, "isNew": false, "luxury": false, "price": {"minValue": null, "maxValue": null, "value": 315000, "formattedValue": "\u20ac 315.000", "formattedValueTop": "\u20ac 315.000", "visible": true, "loweredPrice": null}, "properties": [{"auction": null, "bathrooms": "2", "caption": "VENDITA - LOFT/OPEN SPACE DI 120 MQ RISTRUTTURATO", "category": {"id": 1, "name": "Residenziale"}, "description": "Proponiamo vendita, loft/open space di 120 mq, completamente ristrutturato in ottime condizioni. INTERNO: composto da ingresso su doppio soggiorno open space con cucina a vista, spazio zona notte con cabina armadio e doppi servizi finestrati. L\u2019impianto elettrico \u00e8 stato certificato recentemente. \nDotato di riscaldamento centralizzato a radiatori e aria condizionata. ESTERNO: L\u2019immobile \u00e8 situato al piano seminterrato di 6, in stabile civile anni \u201960 tenuto in buono stato, senza portineria, ma dotata di impresa di pulizie. ZONA: A pochi minuti a piedi vi sono le due metropolitane linea verde, Piazzale Udine e Stazione ferroviaria di Lambrate. \nOttima vicinanza all\u2019uscita Lambrate della tangenziale EST A51, per raggiungere in poco tempo l'aeroporto di Linate. \nVi sono tutti i principali ser", "floor": {"abbreviation": "S", "value": "Seminterrato, con ascensore"}, "multimedia": {"photos": [{"id": 1028074022, "caption": "INGRESSO", "urls": {"small": "https://pwm.im-cdn.it/image/1028074022/xxs-c.jpg"}}, {"id": 1028073938, "caption": "SOGGIORNO", "urls": {"small": "https://pwm.im-cdn.it/image/1028073938/xxs-c.jpg"}}, {"id": 1028073918, "caption": "DISIMPEGNO", "urls": {"small": "https://pwm.im-cdn.it/image/1028073918/xxs-c.jpg"}}, {"id": 1028074014, "caption": "DISIMPEGNO", "urls": {"small": "https://pwm.im-cdn.it/image/1028074014/xxs-c.jpg"}}, {"id": 1028073984, "caption": "SOGGIORNO / CUCINA", "urls": {"small": "https://pwm.im-cdn.it/image/1028073984/xxs-c.jpg"}}, {"id": 1028074018, "caption": "CUCINA", "urls": {"small": "https://pwm.im-cdn.it/image/1028074018/xxs-c.jpg"}}, {"id": 1028074004, "caption": "ZONA NOTTE", "urls": {"small": "https://pwm.im-cdn.it/image/1028074004/xxs-c.jpg"}}, {"id": 1028073930, "caption": "CABINA ARMADIO", "urls": {"small": "https://pwm.im-cdn.it/image/1028073930/xxs-c.jpg"}}, {"id": 1028074010, "caption": "BAGNO", "urls": {"small": "https://pwm.im-cdn.it/image/1028074010/xxs-c.jpg"}}, {"id": 1028073992, "caption": "BAGNO", "urls": {"small": "https://pwm.im-cdn.it/image/1028073992/xxs-c.jpg"}}, {"id": 1028074026, "caption": "BAGNO", "urls": {"small": "https://pwm.im-cdn.it/image/1028074026/xxs-c.jpg"}}], "virtualTours": [], "hasMultimedia": true}, "photo": {"id": 1028074022, "caption": "INGRESSO", "urls": {"thumb": null, "small": "https://pwm.im-cdn.it/image/1028074022/xxs-c.jpg", "medium": null, "large": null}}, "price": {"minValue": null, "maxValue": null, "value": 315000, "formattedValue": "\u20ac 315.000", "formattedValueTop": "\u20ac 315.000", "visible": true, "loweredPrice": null}, "rooms": "3", "shop": null, "surface": "120 m\u00b2", "surfaceValue": "120 m\u00b2", "typology": {"id": 18, "name": "Open space"}, "location": {"latitude": 45.4869, "longitude": 9.2416, "marker": "marker"}}], "propertiesCount": null, "saved": null, "title": "Open space via Ponte di Legno 4, Quartiere Feltre, Milano", "type": "ad", "typology": {"id": 18, "name": "Open space"}, "visibility": "premium"}, "seo": {"anchor": "Open space via Ponte di Legno 4, Quartiere Feltre, Milano", "title": "Open space via Ponte di Legno 4, Milano", "metaTitle": "Vendita Open space  in via Ponte di Legno 4 Milano. Ottimo stato, riscaldamento centralizzato, 120 mq, rif. 86462322", "url": "https://www.immobiliare.it/annunci/86462322/"}}], "breadcrumbs": [{"label": "Immobiliare.it", "link": {"url": "https://www.immobiliare.it/"}}, {"label": "Provincia di Milano", "link": {"url": "https://www.immobiliare.it/vendita-case/milano-provincia/"}, "type": "provincia"}, {"label": "Milano", "link": {"url": "https://www.immobiliare.it/vendita-case/milano/"}, "type": "comune"}, {"label": "Udine, Lambrate", "links": null, "link": {"url": "https://www.immobiliare.it/vendita-case/milano/udine-lambrate/"}, "type": "zona"}, {"label": "Quartiere Feltre", "link": {"url": "https://www.immobiliare.it/vendita-case/milano/quartiere-feltre/"}, "type": "quartiere", "items": [{"label": "Lambrate", "title": " Lambrate", "link": {"url": "https://www.immobiliare.it/vendita-case/milano/lambrate/", "follow": true, "current": false}}, {"label": "Ortica", "title": " Ortica", "link": {"url": "https://www.immobiliare.it/vendita-case/milano/ortica/", "follow": true, "current": false}}, {"label": "Parco Lambro", "title": " Parco Lambro", "link": {"url": "https://www.immobiliare.it/vendita-case/milano/parco-lambro/", "follow": false, "current": false}}, {"label": "Quartiere Feltre", "title": " Quartiere Feltre", "link": {"url": "https://www.immobiliare.it/vendita-case/milano/quartiere-feltre/", "follow": true, "current": true}}, {"label": "Rubattino", "title": " Rubattino", "link": {"url": "https://www.immobiliare.it/vendita-case/milano/rubattino/", "follow": true, "current": false}}, {"label": "Udine", "title": " Udine", "link": {"url": "https://www.immobiliare.it/vendita-case/milano/udine/", "follow": true, "current": false}}]}], "agencies": [], "seoData": {"title": "Case in vendita in zona Quartiere Feltre, Milano - Pag. 2 - Immobiliare.it", "subtitle": "case in vendita zona Quartiere Feltre a Milano", "description": "29 annunci di case in vendita a Quartiere Feltre, Milano da 145.000 euro. Scopri tutti gli annunci privati e di agenzie e scegli con Immobiliare.it la tua futura casa.", "searchName": "Case in vendita a Milano", "facebookSettings": {"prefix": "", "title": "Case in vendita in zona Quartiere Feltre, Milano - Pag. 2 - Immobiliare.it", "description": "29 annunci di case in vendita a Quartiere Feltre, Milano da 145.000 euro. Scopri tutti gli annunci privati e di agenzie e scegli con Immobiliare.it la tua futura casa.", "image": "", "subtitle": "case in vendita zona Quartiere Feltre a Milano"}, "robots": "noindex,follow", "alternate": [{"rel": "alternate", "hreflang": "en", "href": "https://www.immobiliare.it/en/vendita-case/milano/quartiere-feltre/?pag=2"}, {"rel": "alternate", "hreflang": "de", "href": "https://www.immobiliare.it/de/vendita-case/milano/quartiere-feltre/?pag=2"}, {"rel": "alternate", "hreflang": "es", "href": "https://www.immobiliare.it/es/vendita-case/milano/quartiere-feltre/?pag=2"}, {"rel": "alternate", "hreflang": "fr", "href": "https://www.immobiliare.it/fr/vendita-case/milano/quartiere-feltre/?pag=2"}, {"rel": "alternate", "hreflang": "el", "href": "https://www.immobiliare.it/el/vendita-case/milano/quartiere-feltre/?pag=2"}, {"rel": "alternate", "hreflang": "pt", "href": "https://www.immobiliare.it/pt/vendita-case/milano/quartiere-feltre/?pag=2"}, {"rel": "alternate", "hreflang": "ru", "href": "https://www.immobiliare.it/ru/vendita-case/milano/quartiere-feltre/?pag=2"}, {"rel": "alternate", "hreflang": "it", "href": "https://www.immobiliare.it/vendita-case/milano/quartiere-feltre/?pag=2"}, {"rel": "alternate", "hreflang": "x-default", "href": "https://www.immobiliare.it/vendita-case/milano/quartiere-feltre/?pag=2"}], "canonical": "https://www.immobiliare.it/vendita-case/milano/quartiere-feltre/?pag=2", "appleItunesApp": {"appId": 335948517, "affiliateData": "ct=Smart-banner-safari&pt=304468", "appArgument": "immogrp2://urlrev=2"}, "prevPage": "https://www.immobiliare.it/vendita-case/milano/quartiere-feltre/", "nextPage": null}, "relatedSearches": {"title": "Annunci immobiliari Quartiere Feltre", "data": [{"type": "feature-group", "titleList": "Case in vendita a Quartiere Feltre con:", "data": [{"text": "ascensore", "link": {"url": "https://www.immobiliare.it/vendita-case/milano/quartiere-feltre/con-ascensore/"}}, {"text": "cantina", "link": {"url": "https://www.immobiliare.it/vendita-case/milano/quartiere-feltre/con-cantina/"}}, {"text": "terrazzo", "link": {"url": "https://www.immobiliare.it/vendita-case/milano/quartiere-feltre/con-terrazzo/"}}, {"text": "giardino", "link": {"url": "https://www.immobiliare.it/vendita-case/milano/quartiere-feltre/con-giardino/"}}, {"text": "piano terra", "link": {"url": "https://www.immobiliare.it/vendita-case/milano/quartiere-feltre/con-piano-terra/"}}, {"text": "piani intermedi", "link": {"url": "https://www.immobiliare.it/vendita-case/milano/quartiere-feltre/con-piani-intermedi/"}}, {"text": "aria condizionata", "link": {"url": "https://www.immobiliare.it/vendita-case/milano/quartiere-feltre/con-aria-condizionata/"}}]}, {"titleList": "Ricerche correlate", "data": [{"text": "agenzie immobiliari Milano", "link": {"url": "https://www.immobiliare.it/agenzie-immobiliari/milano/"}}, {"text": "prezzi case", "link": {"url": "https://www.immobiliare.it/mercato-immobiliare/lombardia/milano/udine-lambrate/"}}]}]}, "suggestedSearchData": {"token": "5f35be285933b797f60d3a6c90ee05bd", "verticaleSito": "annunci_residenziali"}, "currentPage": 2, "maxPages": 2}