{"count": 104, "totalAds": 104, "isResultsLimitReached": false, "results": [{"realEstate": {"advertiser": {"agency": {"id": 122569, "type": "agency", "label": "agenzia", "displayName": "MONTI32 Immobili", "imageUrls": {"small": "https://pic.im-cdn.it/imagenoresize/240587750.jpg", "large": "https://pic.im-cdn.it/imagenoresize/240587753.jpg"}, "agencyUrl": "https://www.immobiliare.it/agenzie-immobiliari/122569/monti/", "phones": [{"type": "tel1", "value": "02 498 4412"}], "isPaid": true, "customType": null, "externalLinks": null, "text": null, "track": null, "guaranteed": null}, "supervisor": null, "hasCallNumbers": true}, "contract": "sale", "id": 73861282, "isNew": false, "luxury": true, "price": {"minValue": null, "maxValue": null, "value": 3000000, "formattedValue": "\u20ac 3.000.000", "formattedValueTop": "\u20ac 3.000.000", "visible": true, "loweredPrice": null}, "properties": [{"auction": null, "bathrooms": "3", "caption": "Attico panoramico MM S. Agostino", "category": {"id": 1, "name": "Residenziale"}, "description": "Rif: T561I - Via San Calocero \u2013 MM S. Agostino. In contesto di nuova costruzione con servizio di portineria e ascensore, luminosissimo e silenzioso Attico su due livelli. Al piano quarto 225 mq - ingresso, grande soggiorno, ampia cucina abitabile con lavanderia, tre camere da letto, tripli servizi, tre balconi; al piano quinto - serra di 60 mq e ampio terrazzo panoramico di 170 mq. Nuovo, mai abitato. Riscaldamento centralizzato, aria condizionata. Video citofono, porta blindata. Possibilit\u00e0 box auto in acquisto. Prezzo \u20ac 3.000.000,00. Certificazione energetica A \u2013 60,75 kWh/mqa. Per informazioni tel. 024984412 Monti32 Immobili www.monti32.it", "floor": {"abbreviation": "5", "value": "5\u00b0, con ascensore"}, "multimedia": {"photos": [{"id": 999144410, "caption": "terrazzo", "urls": {"small": "https://pwm.im-cdn.it/image/999144410/xxs-c.jpg"}}, {"id": 999144402, "caption": "serra", "urls": {"small": "https://pwm.im-cdn.it/image/999144402/xxs-c.jpg"}}, {"id": 999144412, "caption": "terrazzo", "urls": {"small": "https://pwm.im-cdn.it/image/999144412/xxs-c.jpg"}}, {"id": 999144416, "caption": "terrazzo", "urls": {"small": "https://pwm.im-cdn.it/image/999144416/xxs-c.jpg"}}, {"id": 999144418, "caption": "serra", "urls": {"small": "https://pwm.im-cdn.it/image/999144418/xxs-c.jpg"}}, {"id": 999144428, "caption": "serra", "urls": {"small": "https://pwm.im-cdn.it/image/999144428/xxs-c.jpg"}}, {"id": 999144432, "caption": "salone", "urls": {"small": "https://pwm.im-cdn.it/image/999144432/xxs-c.jpg"}}, {"id": 999144436, "caption": "salone", "urls": {"small": "https://pwm.im-cdn.it/image/999144436/xxs-c.jpg"}}, {"id": 999144438, "caption": "cucina", "urls": {"small": "https://pwm.im-cdn.it/image/999144438/xxs-c.jpg"}}, {"id": 999144442, "caption": "cucina", "urls": {"small": "https://pwm.im-cdn.it/image/999144442/xxs-c.jpg"}}, {"id": 999144448, "caption": "cucina", "urls": {"small": "https://pwm.im-cdn.it/image/999144448/xxs-c.jpg"}}, {"id": 999144452, "caption": "bagno", "urls": {"small": "https://pwm.im-cdn.it/image/999144452/xxs-c.jpg"}}, {"id": 999144456, "caption": "viste", "urls": {"small": "https://pwm.im-cdn.it/image/999144456/xxs-c.jpg"}}, {"id": 1115913834, "caption": "", "urls": {"small": "https://pwm.im-cdn.it/image/1115913834/xxs-c.jpg"}}, {"id": 1115913844, "caption": "", "urls": {"small": "https://pwm.im-cdn.it/image/1115913844/xxs-c.jpg"}}, {"id": 1115913860, "caption": "", "urls": {"small": "https://pwm.im-cdn.it/image/1115913860/xxs-c.jpg"}}, {"id": 1115913882, "caption": "", "urls": {"small": "https://pwm.im-cdn.it/image/1115913882/xxs-c.jpg"}}, {"id": 1115913900, "caption": "", "urls": {"small": "https://pwm.im-cdn.it/image/1115913900/xxs-c.jpg"}}, {"id": 1115913920, "caption": "", "urls": {"small": "https://pwm.im-cdn.it/image/1115913920/xxs-c.jpg"}}, {"id": 1115913954, "caption": "", "urls": {"small": "https://pwm.im-cdn.it/image/1115913954/xxs-c.jpg"}}], "virtualTours": [null], "hasMultimedia": true}, "photo": {"id": 999144410, "caption": "terrazzo", "urls": {"thumb": null, "small": "https://pwm.im-cdn.it/image/999144410/xxs-c.jpg", "medium": null, "large": null}}, "price": {"minValue": null, "maxValue": null, "value": 3000000, "formattedValue": "\u20ac 3.000.000", "formattedValueTop": "\u20ac 3.000.000", "visible": true, "loweredPrice": null}, "rooms": "5", "shop": null, "surface": "350 m\u00b2", "surfaceValue": "350 m\u00b2", "typology": {"id": 15, "name": "Attico"}, "location": {"latitude": 45.4582, "longitude": 9.175, "marker": "marker"}}], "propertiesCount": null, "saved": null, "title": "Attico via San Calocero, Corso Genova, Milano", "type": "ad", "typology": {"id": 15, "name": "Attico"}, "visibility": "premium"}, "seo": {"anchor": "Attico via San Calocero, Corso Genova, Milano", "title": "Attico via San Calocero, Milano", "metaTitle": "Vendita Attico  in via San Calocero Milano. Nuovo, posto auto, terrazza, rif. 73861282", "url": "https://www.immobiliare.it/annunci/73861282/"}}, {"realEstate": {"advertiser": {"agency": {"id": 236962, "type": "agency", "label": "agenzia", "displayName": "PR Casa", "imageUrls": {"small": "https://pic.im-cdn.it/imagenoresize/752520842.jpg", "large": "https://pic.im-cdn.it/imagenoresize/752520844.jpg"}, "agencyUrl": "https://www.immobiliare.it/agenzie-immobiliari/236962/pr-casa/", "phones": [{"type": "vTel1", "value": "02 3540 6695"}], "isPaid": true, "customType": null, "externalLinks": null, "text": null, "track": null, "guaranteed": null}, "supervisor": null, "hasCallNumbers": true}, "contract": "sale", "id": 71616510, "isNew": false, "luxury": true, "price": {"minValue": null, "maxValue": null, "value": 3000000, "formattedValue": "\u20ac 3.000.000", "formattedValueTop": "\u20ac 3.000.000", "visible": true, "loweredPrice": null}, "properties": [{"auction": null, "bathrooms": "3+", "caption": "Attico Via San Calocero 10", "category": {"id": 1, "name": "Residenziale"}, "description": "In edificio signorile di nuova costruzione, posizionato in zona tranquilla, nelle immediate vicinanze del Centro, proponiamo attico di mq 310 situato ai piani quarto/quinto composto di:\ngrande soggiorno, ampia cucina con annessa lavanderia, 3 camere e tripli servizi al piano quarto, serra di 60mq e ampio terrazzo panoramico al quinto piano. Rifiniture di pregio: pavimentazione integralmente in parquet di prima scelta, rivestimento dei servizi in marmo, vasca idromassaggio angolare jacuzzi, infissi a bassa trasmittanza, tapparelle con comando motorizzato, impianti di riscaldamento e raffrescamento centralizzati ma a gestione e contabilizzazione autonome, impianto d\u2019allarme e videosorveglianza delle parti comuni dell\u2019edificio. L\u2019utilizzo delle migliori soluzioni impiantistiche e di isolament", "floor": {"abbreviation": "A", "value": "Ultimo piano, con ascensore"}, "multimedia": {"photos": [{"id": 757651530, "caption": "Soggiorno", "urls": {"small": "https://pwm.im-cdn.it/image/757651530/xxs-c.jpg"}}, {"id": 757651532, "caption": "Soggiorno", "urls": {"small": "https://pwm.im-cdn.it/image/757651532/xxs-c.jpg"}}, {"id": 757651536, "caption": "Soggiorno", "urls": {"small": "https://pwm.im-cdn.it/image/757651536/xxs-c.jpg"}}, {"id": 757651538, "caption": "Cucina", "urls": {"small": "https://pwm.im-cdn.it/image/757651538/xxs-c.jpg"}}, {"id": 757651540, "caption": "Bagno", "urls": {"small": "https://pwm.im-cdn.it/image/757651540/xxs-c.jpg"}}, {"id": 757651542, "caption": "Balcone", "urls": {"small": "https://pwm.im-cdn.it/image/757651542/xxs-c.jpg"}}, {"id": 757651544, "caption": "Bagno", "urls": {"small": "https://pwm.im-cdn.it/image/757651544/xxs-c.jpg"}}, {"id": 757651546, "caption": "Camera da letto", "urls": {"small": "https://pwm.im-cdn.it/image/757651546/xxs-c.jpg"}}, {"id": 757651548, "caption": "Serra", "urls": {"small": "https://pwm.im-cdn.it/image/757651548/xxs-c.jpg"}}, {"id": 757651550, "caption": "Serra", "urls": {"small": "https://pwm.im-cdn.it/image/757651550/xxs-c.jpg"}}, {"id": 757651552, "caption": "Terrazzo", "urls": {"small": "https://pwm.im-cdn.it/image/757651552/xxs-c.jpg"}}, {"id": 757651554, "caption": "Terrazzo", "urls": {"small": "https://pwm.im-cdn.it/image/757651554/xxs-c.jpg"}}], "virtualTours": [], "hasMultimedia": true}, "photo": {"id": 757651530, "caption": "Soggiorno", "urls": {"thumb": null, "small": "https://pwm.im-cdn.it/image/757651530/xxs-c.jpg", "medium": null, "large": null}}, "price": {"minValue": null, "maxValue": null, "value": 3000000, "formattedValue": "\u20ac 3.000.000", "formattedValueTop": "\u20ac 3.000.000", "visible": true, "loweredPrice": null}, "rooms": "5", "shop": null, "surface": "310 m\u00b2", "surfaceValue": "310 m\u00b2", "typology": {"id": 15, "name": "Attico"}, "location": {"latitude": 45.4582, "longitude": 9.1749, "marker": "marker"}}], "propertiesCount": null, "saved": null, "title": "Attico via San Calocero 10, Corso Genova, Milano", "type": "ad", "typology": {"id": 15, "name": "Attico"}, "visibility": "premium"}, "seo": {"anchor": "Attico via San Calocero 10, Corso Genova, Milano", "title": "Attico via San Calocero 10, Milano", "metaTitle": "Vendita Attico  in via San Calocero 10 Milano. Nuovo, terrazza, rif. 71616510", "url": "https://www.immobiliare.it/annunci/71616510/"}}, {"realEstate": {"advertiser": {"agency": {"id": 236962, "type": "agency", "label": "agenzia", "displayName": "PR Casa", "imageUrls": {"small": "https://pic.im-cdn.it/imagenoresize/752520842.jpg", "large": "https://pic.im-cdn.it/imagenoresize/752520844.jpg"}, "agencyUrl": "https://www.immobiliare.it/agenzie-immobiliari/236962/pr-casa/", "phones": [{"type": "vTel1", "value": "02 3540 6695"}], "isPaid": true, "customType": null, "externalLinks": null, "text": null, "track": null, "guaranteed": null}, "supervisor": null, "hasCallNumbers": true}, "contract": "sale", "id": 71616422, "isNew": false, "luxury": true, "price": {"minValue": null, "maxValue": null, "value": 1750000, "formattedValue": "\u20ac 1.750.000", "formattedValueTop": "\u20ac 1.750.000", "visible": true, "loweredPrice": null}, "properties": [{"auction": null, "bathrooms": "3+", "caption": "Quadrilocale Piano 3 Via San Calocero 10", "category": {"id": 1, "name": "Residenziale"}, "description": "In edificio signorile di nuova costruzione, posizionato in zona tranquilla, nelle immediate vicinanze del Centro, proponiamo quadrilocale di mq 225 situato al piano terzo composto di:\ngrande soggiorno, ampia cucina con annessa lavanderia, 3 camere e tripli servizi. Rifiniture di pregio: pavimentazione integralmente in parquet di prima scelta, rivestimento dei servizi in marmo, vasca idromassaggio angolare jacuzzi, infissi a bassa trasmittanza, tapparelle con comando motorizzato, impianti di riscaldamento e raffrescamento centralizzati ma a gestione e contabilizzazione autonome, impianto d\u2019allarme e videosorveglianza delle parti comuni dell\u2019edificio. L\u2019utilizzo delle migliori soluzioni impiantistiche e di isolamento termico-acustico hanno permesso di ottenere una qualificazione energetica d", "floor": {"abbreviation": "3", "value": "3\u00b0, con ascensore"}, "multimedia": {"photos": [{"id": 757650966, "caption": "Soggiorno", "urls": {"small": "https://pwm.im-cdn.it/image/757650966/xxs-c.jpg"}}, {"id": 757650960, "caption": "Soggiorno", "urls": {"small": "https://pwm.im-cdn.it/image/757650960/xxs-c.jpg"}}, {"id": 757650962, "caption": "Soggiorno", "urls": {"small": "https://pwm.im-cdn.it/image/757650962/xxs-c.jpg"}}, {"id": 757650964, "caption": "Soggiorno", "urls": {"small": "https://pwm.im-cdn.it/image/757650964/xxs-c.jpg"}}, {"id": 757650958, "caption": "Soggiorno", "urls": {"small": "https://pwm.im-cdn.it/image/757650958/xxs-c.jpg"}}, {"id": 757650968, "caption": "Bagno", "urls": {"small": "https://pwm.im-cdn.it/image/757650968/xxs-c.jpg"}}, {"id": 757650970, "caption": "Camera da letto", "urls": {"small": "https://pwm.im-cdn.it/image/757650970/xxs-c.jpg"}}, {"id": 757650972, "caption": "Bagno", "urls": {"small": "https://pwm.im-cdn.it/image/757650972/xxs-c.jpg"}}, {"id": 757650974, "caption": "Camera da letto", "urls": {"small": "https://pwm.im-cdn.it/image/757650974/xxs-c.jpg"}}], "virtualTours": [], "hasMultimedia": true}, "photo": {"id": 757650966, "caption": "Soggiorno", "urls": {"thumb": null, "small": "https://pwm.im-cdn.it/image/757650966/xxs-c.jpg", "medium": null, "large": null}}, "price": {"minValue": null, "maxValue": null, "value": 1750000, "formattedValue": "\u20ac 1.750.000", "formattedValueTop": "\u20ac 1.750.000", "visible": true, "loweredPrice": null}, "rooms": "4", "shop": null, "surface": "225 m\u00b2", "surfaceValue": "225 m\u00b2", "typology": {"id": 14, "name": "Appartamento"}, "location": {"latitude": 45.4582, "longitude": 9.1749, "marker": "marker"}}], "propertiesCount": null, "saved": null, "title": "Quadrilocale via San Calocero 10, Corso Genova, Milano", "type": "ad", "typology": {"id": 14, "name": "Appartamento"}, "visibility": "premium"}, "seo": {"anchor": "Quadrilocale via San Calocero 10, Corso Genova, Milano", "title": "Quadrilocale via San Calocero 10, Milano", "metaTitle": "Vendita Appartamento Milano. Quadrilocale in via San Calocero 10. Nuovo, terzo piano, terrazza, riscaldamento centralizzato, rif. 71616422", "url": "https://www.immobiliare.it/annunci/71616422/"}}, {"realEstate": {"advertiser": {"agency": {"id": 218100, "type": "agency", "label": "agenzia", "displayName": "Immobiliare Milanese Srl", "imageUrls": null, "agencyUrl": "https://www.immobiliare.it/agenzie-immobiliari/218100/fossati-milano/", "phones": [{"type": "vTel1", "value": "02 8974 7216"}], "isPaid": true, "customType": null, "externalLinks": null, "text": null, "track": null, "guaranteed": null}, "supervisor": null, "hasCallNumbers": true}, "contract": "sale", "id": 69709480, "isNew": false, "luxury": false, "price": {"minValue": null, "maxValue": null, "value": 235000, "formattedValue": "\u20ac 235.000", "formattedValueTop": "\u20ac 235.000", "visible": true, "loweredPrice": null}, "properties": [{"auction": null, "bathrooms": "1", "caption": "Monolocale", "category": {"id": 1, "name": "Residenziale"}, "description": "Monolocale, completamente ristrutturato, circa mq. 50, composto da soggiorno angolo cottura, divano letto, disimpegno e bagno.\nOttimo investimento.", "floor": {"abbreviation": "T", "value": "Piano terra, con ascensore"}, "multimedia": {"photos": [{"id": 1007597097, "caption": "", "urls": {"small": "https://pwm.im-cdn.it/image/1007597097/xxs-c.jpg"}}, {"id": 722773284, "caption": "", "urls": {"small": "https://pwm.im-cdn.it/image/722773284/xxs-c.jpg"}}, {"id": 1007597139, "caption": "", "urls": {"small": "https://pwm.im-cdn.it/image/1007597139/xxs-c.jpg"}}, {"id": 722773288, "caption": "", "urls": {"small": "https://pwm.im-cdn.it/image/722773288/xxs-c.jpg"}}, {"id": 1021891876, "caption": "", "urls": {"small": "https://pwm.im-cdn.it/image/1021891876/xxs-c.jpg"}}, {"id": 1021892318, "caption": "", "urls": {"small": "https://pwm.im-cdn.it/image/1021892318/xxs-c.jpg"}}, {"id": 1021891976, "caption": "", "urls": {"small": "https://pwm.im-cdn.it/image/1021891976/xxs-c.jpg"}}, {"id": 722773298, "caption": "", "urls": {"small": "https://pwm.im-cdn.it/image/722773298/xxs-c.jpg"}}, {"id": 722773302, "caption": "", "urls": {"small": "https://pwm.im-cdn.it/image/722773302/xxs-c.jpg"}}, {"id": 722773304, "caption": "", "urls": {"small": "https://pwm.im-cdn.it/image/722773304/xxs-c.jpg"}}, {"id": 722773290, "caption": "", "urls": {"small": "https://pwm.im-cdn.it/image/722773290/xxs-c.jpg"}}, {"id": 722773314, "caption": "", "urls": {"small": "https://pwm.im-cdn.it/image/722773314/xxs-c.jpg"}}, {"id": 722773316, "caption": "", "urls": {"small": "https://pwm.im-cdn.it/image/722773316/xxs-c.jpg"}}, {"id": 722773318, "caption": "", "urls": {"small": "https://pwm.im-cdn.it/image/722773318/xxs-c.jpg"}}, {"id": 722773280, "caption": "", "urls": {"small": "https://pwm.im-cdn.it/image/722773280/xxs-c.jpg"}}, {"id": 1007597281, "caption": "", "urls": {"small": "https://pwm.im-cdn.it/image/1007597281/xxs-c.jpg"}}, {"id": 1007597529, "caption": "", "urls": {"small": "https://pwm.im-cdn.it/image/1007597529/xxs-c.jpg"}}, {"id": 722773292, "caption": "", "urls": {"small": "https://pwm.im-cdn.it/image/722773292/xxs-c.jpg"}}, {"id": 1021892610, "caption": "", "urls": {"small": "https://pwm.im-cdn.it/image/1021892610/xxs-c.jpg"}}, {"id": 1021892646, "caption": "", "urls": {"small": "https://pwm.im-cdn.it/image/1021892646/xxs-c.jpg"}}], "virtualTours": [], "hasMultimedia": true}, "photo": {"id": 1007597097, "caption": "", "urls": {"thumb": null, "small": "https://pwm.im-cdn.it/image/1007597097/xxs-c.jpg", "medium": null, "large": null}}, "price": {"minValue": null, "maxValue": null, "value": 235000, "formattedValue": "\u20ac 235.000", "formattedValueTop": "\u20ac 235.000", "visible": true, "loweredPrice": null}, "rooms": "1", "shop": null, "surface": "50 m\u00b2", "surfaceValue": "50 m\u00b2", "typology": {"id": 14, "name": "Appartamento"}, "location": {"latitude": 45.4563, "longitude": 9.1758, "marker": "marker"}}], "propertiesCount": null, "saved": null, "title": "Monolocale via Cicco Simonetta 11/A, Corso Genova, Milano", "type": "ad", "typology": {"id": 14, "name": "Appartamento"}, "visibility": "top"}, "seo": {"anchor": "Monolocale via Cicco Simonetta 11/A, Corso Genova, Milano", "title": "Monolocale via Cicco Simonetta 11/A, Milano", "metaTitle": "Vendita Appartamento Milano. Monolocale in via Cicco Simonetta 11/A. Ottimo stato, piano terra, riscaldamento autonomo, rif. 69709480", "url": "https://www.immobiliare.it/annunci/69709480/"}}], "breadcrumbs": [{"label": "Immobiliare.it", "link": {"url": "https://www.immobiliare.it/"}}, {"label": "Provincia di Milano", "link": {"url": "https://www.immobiliare.it/vendita-case/milano-provincia/"}, "type": "provincia"}, {"label": "Milano", "link": {"url": "https://www.immobiliare.it/vendita-case/milano/"}, "type": "comune"}, {"label": "Genova, Ticinese", "links": null, "link": {"url": "https://www.immobiliare.it/vendita-case/milano/genova-ticinese/"}, "type": "zona"}, {"label": "Corso Genova", "link": {"url": "https://www.immobiliare.it/vendita-case/milano/corso-genova/"}, "type": "quartiere", "items": [{"label": "Corso Genova", "title": " Corso Genova", "link": {"url": "https://www.immobiliare.it/vendita-case/milano/corso-genova/", "follow": true, "current": true}}, {"label": "San Vittore", "title": " San Vittore", "link": {"url": "https://www.immobiliare.it/vendita-case/milano/san-vittore/", "follow": true, "current": false}}, {"label": "Ticinese", "title": " Ticinese", "link": {"url": "https://www.immobiliare.it/vendita-case/milano/ticinese/", "follow": true, "current": false}}]}], "agencies": [], "seoData": {"title": "Case in vendita in zona Corso Genova, Milano - Pag. 5 - Immobiliare.it", "subtitle": "case in vendita zona Corso Genova a Milano", "description": "104 annunci di case in vendita a Corso Genova, Milano da 138.000 euro. Scopri tutti gli annunci privati e di agenzie e scegli con Immobiliare.it la tua futura casa.", "searchName": "Case in vendita a Milano", "facebookSettings": {"prefix": "", "title": "Case in vendita in zona Corso Genova, Milano - Pag. 5 - Immobiliare.it", "description": "104 annunci di case in vendita a Corso Genova, Milano da 138.000 euro. Scopri tutti gli annunci privati e di agenzie e scegli con Immobiliare.it la tua futura casa.", "image": "", "subtitle": "case in vendita zona Corso Genova a Milano"}, "robots": "noindex,follow", "alternate": [{"rel": "alternate", "hreflang": "en", "href": "https://www.immobiliare.it/en/vendita-case/milano/corso-genova/?pag=5"}, {"rel": "alternate", "hreflang": "de", "href": "https://www.immobiliare.it/de/vendita-case/milano/corso-genova/?pag=5"}, {"rel": "alternate", "hreflang": "es", "href": "https://www.immobiliare.it/es/vendita-case/milano/corso-genova/?pag=5"}, {"rel": "alternate", "hreflang": "fr", "href": "https://www.immobiliare.it/fr/vendita-case/milano/corso-genova/?pag=5"}, {"rel": "alternate", "hreflang": "el", "href": "https://www.immobiliare.it/el/vendita-case/milano/corso-genova/?pag=5"}, {"rel": "alternate", "hreflang": "pt", "href": "https://www.immobiliare.it/pt/vendita-case/milano/corso-genova/?pag=5"}, {"rel": "alternate", "hreflang": "ru", "href": "https://www.immobiliare.it/ru/vendita-case/milano/corso-genova/?pag=5"}, {"rel": "alternate", "hreflang": "it", "href": "https://www.immobiliare.it/vendita-case/milano/corso-genova/?pag=5"}, {"rel": "alternate", "hreflang": "x-default", "href": "https://www.immobiliare.it/vendita-case/milano/corso-genova/?pag=5"}], "canonical": "https://www.immobiliare.it/vendita-case/milano/corso-genova/?pag=5", "appleItunesApp": {"appId": 335948517, "affiliateData": "ct=Smart-banner-safari&pt=304468", "appArgument": "immogrp2://urlrev=2"}, "prevPage": "https://www.immobiliare.it/vendita-case/milano/corso-genova/?pag=4", "nextPage": null}, "relatedSearches": {"title": "Annunci immobiliari Corso Genova", "data": [{"type": "feature-group", "titleList": "Case in vendita a Corso Genova con:", "data": [{"text": "ascensore", "link": {"url": "https://www.immobiliare.it/vendita-case/milano/corso-genova/con-ascensore/"}}, {"text": "garage", "link": {"url": "https://www.immobiliare.it/vendita-case/milano/corso-genova/con-garage/"}}, {"text": "cantina", "link": {"url": "https://www.immobiliare.it/vendita-case/milano/corso-genova/con-cantina/"}}, {"text": "terrazzo", "link": {"url": "https://www.immobiliare.it/vendita-case/milano/corso-genova/con-terrazzo/"}}, {"text": "giardino", "link": {"url": "https://www.immobiliare.it/vendita-case/milano/corso-genova/con-giardino/"}}, {"text": "piano terra", "link": {"url": "https://www.immobiliare.it/vendita-case/milano/corso-genova/con-piano-terra/"}}, {"text": "piani intermedi", "link": {"url": "https://www.immobiliare.it/vendita-case/milano/corso-genova/con-piani-intermedi/"}}, {"text": "riscaldamento autonomo", "link": {"url": "https://www.immobiliare.it/vendita-case/milano/corso-genova/con-riscaldamento-autonomo/"}}, {"text": "aria condizionata", "link": {"url": "https://www.immobiliare.it/vendita-case/milano/corso-genova/con-aria-condizionata/"}}]}, {"titleList": "Ricerche correlate", "data": [{"text": "agenzie immobiliari Milano", "link": {"url": "https://www.immobiliare.it/agenzie-immobiliari/milano/"}}, {"text": "prezzi case", "link": {"url": "https://www.immobiliare.it/mercato-immobiliare/lombardia/milano/genova-ticinese/"}}, {"text": "case di lusso", "link": {"url": "https://www.immobiliare.it/vendita-case/milano/corso-genova/con-lusso/"}}]}]}, "suggestedSearchData": {"token": "a7bb9824df960cbb4578465cf7f11cca", "verticaleSito": "annunci_residenziali"}, "currentPage": 5, "maxPages": 5}